gym_cap/__init__.py
gym_cap/envs/__init__.py
gym_cap/envs/agent.py
gym_cap/envs/cap_env.py
gym_cap/envs/const.py
gym_cap/envs/create_map.py
gym_cap/envs/default.ini
gym_cap/heuristic/__init__.py
gym_cap/heuristic/astar_flag.py
gym_cap/heuristic/defense.py
gym_cap/heuristic/fighter.py
gym_cap/heuristic/patrol.py
gym_cap/heuristic/policy.py
gym_cap/heuristic/random.py
gym_cap/heuristic/roomba.py
gym_cap/heuristic/spiral.py
gym_cap/heuristic/zeros.py
gym_cap-0.1.4.12.dist-info/LICENSE.md
gym_cap-0.1.4.12.dist-info/METADATA
gym_cap-0.1.4.12.dist-info/WHEEL
gym_cap-0.1.4.12.dist-info/top_level.txt
gym_cap-0.1.4.12.dist-info/RECORD
