Metadata-Version: 2.1
Name: gym-cap
Version: 0.1.4.12
Summary: UNKNOWN
Home-page: https://github.com/raide-project/ctf_public
Author: DOs, skim449
Author-email: UNKNOWN
License: MIT
Platform: UNKNOWN
Requires-Dist: gym (>=0.16.0)
Requires-Dist: numpy (>=1.18.1)
